LICENSE
computlib/.gitignore
computlib/__init__.py
computlib/main.py
computlib/tools.py
computlib-0.4.3.dist-info/LICENSE
computlib-0.4.3.dist-info/WHEEL
computlib-0.4.3.dist-info/METADATA
computlib-0.4.3.dist-info/RECORD
